{"otherData": {},"traceEvents":[{},{"cat":"function","dur":401305,"name":"glfwInit","ph":"X","pid":0,"tid":11820,"ts":488461844581.700},{"cat":"function","dur":452861,"name":"glfwCreateWindow","ph":"X","pid":0,"tid":11820,"ts":488462250814.800},{"cat":"function","dur":62,"name":"class std::unique_ptr<class GraphicsContext,struct std::default_delete<class GraphicsContext> > __cdecl GraphicsContext::Create(void *)","ph":"X","pid":0,"tid":11820,"ts":488462703906.300},{"cat":"function","dur":66047,"name":"void __cdecl OpenGLContext::Init(void)","ph":"X","pid":0,"tid":11820,"ts":488462704157.800},{"cat":"function","dur":0,"name":"void __cdecl WindowsWindow::SetVSync(bool)","ph":"X","pid":0,"tid":11820,"ts":488462770409.000},{"cat":"function","dur":937158,"name":"void __cdecl WindowsWindow::Init(const struct WindowProps &)","ph":"X","pid":0,"tid":11820,"ts":488461833349.700},{"cat":"function","dur":937283,"name":"__cdecl WindowsWindow::WindowsWindow(const struct WindowProps &)","ph":"X","pid":0,"tid":11820,"ts":488461833349.000}]}